pulumi_supavisor_native/__init__.py
pulumi_supavisor_native/_utilities.py
pulumi_supavisor_native/provider.py
pulumi_supavisor_native/pulumi-plugin.json
pulumi_supavisor_native/py.typed
pulumi_supavisor_native/config/__init__.py
pulumi_supavisor_native/config/__init__.pyi
pulumi_supavisor_native/config/vars.py
pulumi_supavisor_native/tenants/__init__.py
pulumi_supavisor_native/tenants/_inputs.py
pulumi_supavisor_native/tenants/get_tenant.py
pulumi_supavisor_native/tenants/outputs.py
pulumi_supavisor_native/tenants/tenant.py
pulumi_supavisor_native-0.0.6.dist-info/METADATA
pulumi_supavisor_native-0.0.6.dist-info/WHEEL
pulumi_supavisor_native-0.0.6.dist-info/top_level.txt
pulumi_supavisor_native-0.0.6.dist-info/RECORD
