Metadata-Version: 2.4
Name: pulumi_supavisor_native
Version: 0.0.6
Summary: A Pulumi package for creating and managing SupavisorNative resources.
License: Apache-2.0
Project-URL: Homepage, https://github.com/phillarson-xyz/pulumi-supavisor-native
Project-URL: Repository, https://github.com/phillarson-xyz/pulumi-supavisor-native
Keywords: pulumi,supavisor-native,category/cloud,kind/native
Requires-Python: >=3.9
Requires-Dist: parver>=0.2.1
Requires-Dist: pulumi<4.0.0,>=3.0.0
Requires-Dist: semver>=2.8.1
Requires-Dist: typing-extensions>=4.11; python_version < "3.11"
